.gitattributes
.gitignore
.travis.yml
README.md
setup.cfg
setup.py
asserted/__init__.py
asserted/asserted.py
asserted/cli.py
asserted/example_class.py
asserted/utils.py
asserted.egg-info/PKG-INFO
asserted.egg-info/SOURCES.txt
asserted.egg-info/dependency_links.txt
asserted.egg-info/entry_points.txt
asserted.egg-info/top_level.txt
tests/__init__.py
tests/conftest.py
tests/test_asserted.py
tests/test_cli.py
tests/test_utils.py
tests/txt/test_asserted_as_function_hello.txt
tests/txt/test_assertedex.txt
tests/txt/test_ex.txt
tests/txt/test_hey.txt
tests/txt/test_multiex.txt